snowflake_bronze_to_silver_mapper-0.0.0.dist-info/licenses/LICENSE
snowflake_pipeline/__init__.py
snowflake_pipeline/__main__.py
snowflake_pipeline/cli.py
snowflake_pipeline/config.py
snowflake_pipeline/docker_manager.py
snowflake_pipeline/templates/backend-Dockerfile
snowflake_pipeline/templates/config.json
snowflake_pipeline/templates/docker-compose.yml
snowflake_pipeline/templates/frontend-Dockerfile
snowflake_bronze_to_silver_mapper-0.0.0.dist-info/METADATA
snowflake_bronze_to_silver_mapper-0.0.0.dist-info/WHEEL
snowflake_bronze_to_silver_mapper-0.0.0.dist-info/entry_points.txt
snowflake_bronze_to_silver_mapper-0.0.0.dist-info/top_level.txt
snowflake_bronze_to_silver_mapper-0.0.0.dist-info/RECORD
