Metadata-Version: 2.4
Name: snowflake-bronze-to-silver-mapper
Version: 0.0.0
Summary: Transform Bronze to Silver layer data in Snowflake
Author-email: Brunda V <brunda8496@gmail.com>
License: MIT
Project-URL: Homepage, https://github.com/brundavadiga/snowflake-bronze-to-silver-mapper
Project-URL: Documentation, https://snowflake-mapper.readthedocs.io
Project-URL: Repository, https://github.com/brundavadiga/snowflake-bronze-to-silver-mapper
Project-URL: Bug Tracker, https://github.com/brundavadiga/snowflake-bronze-to-silver-mapper/issues
Keywords: snowflake,data-engineering,etl,bronze-to-silver,cpg
Classifier: Development Status :: 4 - Beta
Classifier: Intended Audience :: Developers
Classifier: License :: OSI Approved :: MIT License
Classifier: Programming Language :: Python :: 3
Requires-Python: >=3.8
License-File: LICENSE
Requires-Dist: docker>=6.0.0
Requires-Dist: snowflake-connector-python>=3.0.0
Requires-Dist: python-dotenv>=0.19.0
Requires-Dist: click>=8.0.0
Requires-Dist: python-dotenv>=1.0.0
Requires-Dist: pyyaml>=6.0
Requires-Dist: rich>=13.0.0
Requires-Dist: requests>=2.28.0
Dynamic: license-file
